kerpy/__init__.py
kerpy/_version.py
kerpy/diff.py
kerpy/processing.py
kerpy/shapes.py
KernelsPython-1.0.5.dist-info/LICENSE
KernelsPython-1.0.5.dist-info/METADATA
KernelsPython-1.0.5.dist-info/WHEEL
KernelsPython-1.0.5.dist-info/top_level.txt
KernelsPython-1.0.5.dist-info/RECORD
