Metadata-Version: 2.1
Name: KernelsPython
Version: 1.0.5
Summary: A Python library to generate 2D-kernels for convolutions, mathematical morphology and more
Author: Simon Bertrand
Author-email: simonbertrand.contact@gmail.com
License: GPL-3.0
Classifier: Programming Language :: Python :: 3
Classifier: License :: OSI Approved :: GNU General Public License v3 (GPLv3)
Classifier: Operating System :: OS Independent
Requires-Python: >=3.6
License-File: LICENSE
Requires-Dist: numpy
Requires-Dist: wheel
Requires-Dist: setuptools
Requires-Dist: twine
Requires-Dist: pytest
Requires-Dist: pytest-runner
Requires-Dist: sphinx
Requires-Dist: sphinx-book-theme
Requires-Dist: ipykernel
Requires-Dist: pylint
Requires-Dist: versioneer
